Metadata-Version: 2.1
Name: string-cleaner
Version: 0.2.1
Summary: Module for clean string from special chars and replace it by html-entity.
Home-page: https://github.com/Oficerov/string_cleaner
Author: v.oficerov
Author-email: valeryoficerov@gmail.com
License: MIT
Download-URL: https://github.com/Oficerov/string_cleaner/archive/refs/heads/master.zip
Project-URL: Bug Tracker, https://github.com/Oficerov/string_cleaner/issues
Keywords: xss,sql,cleaner,string
Platform: any
Classifier: License :: OSI Approved :: MIT License
Classifier: Operating System :: OS Independent
Classifier: Intended Audience :: Developers
Classifier: Programming Language :: Python
Classifier: Programming Language :: Python :: 3.10
Classifier: Topic :: Software Development :: Libraries :: Python Modules
Requires-Python: >=3.10
License-File: LICENSE
